model2gguf/__init__.py
model2gguf/converter.py
model2gguf-1.0.0.dist-info/METADATA
model2gguf-1.0.0.dist-info/WHEEL
model2gguf-1.0.0.dist-info/entry_points.txt
model2gguf-1.0.0.dist-info/top_level.txt
model2gguf-1.0.0.dist-info/RECORD
