Metadata-Version: 2.1
Name: model2gguf
Version: 1.0.0
Summary: A tool to convert Hugging Face models to GGUF format and manage Ollama models.
Home-page: https://github.com/RahulPatnaik/model2gguf
Author: Rahul Patnaik, Krishna Dvaipayan
Author-email: rpatnaik2005@gmail.com, krishnadvaipayan.ei21@rvce.edu.in
License: MIT
Classifier: Programming Language :: Python :: 3
Classifier: License :: OSI Approved :: MIT License
Classifier: Operating System :: OS Independent
Requires-Python: >=3.6
Requires-Dist: huggingface-hub
